{
  "title": "Contact",
  "links": [
    {
      "name": "Email",
      "faIcon": "fa-envelope-o",
      "url": "mailto:malerei@leissmann.com?subject=commission",
      "text": "malerei@leissmann.com"
    },
    {
      "name": "Artwork",
      "faIcon": "fa-external-link",
      "url": "http://www.leissmann.com",
      "text": "www.leissmann.com"
    },
    {
      "name": "Twitch",
      "faIcon": "fa-twitch",
      "url": "https://www.twitch.tv/jele77",
      "text": "www.twitch.tv/jele77"
    },
    {
      "name": "Twitter",
      "faIcon": "fa-twitter",
      "url": "https://twitter.com/jele77hs",
      "text": "twitter.com/jele77"
    }
  ]
}
